nuclei_grpc-1.0.0.dist-info/licenses/LICENSE
nuclei_server/__init__.py
nuclei_server/auth.py
nuclei_server/child_mode.py
nuclei_server/cli_client.py
nuclei_server/distributed.py
nuclei_server/executor.py
nuclei_server/nuclei_pb2.py
nuclei_server/nuclei_pb2_grpc.py
nuclei_server/server.py
nuclei_server/web_ui.py
nuclei_grpc-1.0.0.dist-info/METADATA
nuclei_grpc-1.0.0.dist-info/WHEEL
nuclei_grpc-1.0.0.dist-info/entry_points.txt
nuclei_grpc-1.0.0.dist-info/top_level.txt
nuclei_grpc-1.0.0.dist-info/RECORD
