Metadata-Version: 2.4
Name: nuclei-grpc
Version: 1.0.0
Summary: Distributed Nuclei scanner with gRPC server and web UI
Home-page: https://github.com/yourusername/nuclei-grpc
Author: Recon Tasks
License: MIT
Project-URL: Homepage, https://github.com/yourusername/nuclei-grpc
Project-URL: Documentation, https://github.com/yourusername/nuclei-grpc#readme
Project-URL: Repository, https://github.com/yourusername/nuclei-grpc.git
Keywords: nuclei,grpc,scanner,security,distributed
Classifier: Programming Language :: Python :: 3
Classifier: Programming Language :: Python :: 3.11
Classifier: Programming Language :: Python :: 3.12
Classifier: License :: OSI Approved :: MIT License
Classifier: Operating System :: OS Independent
Classifier: Development Status :: 4 - Beta
Classifier: Intended Audience :: Developers
Classifier: Topic :: Software Development :: Libraries :: Python Modules
Classifier: Topic :: Internet :: WWW/HTTP :: Dynamic Content
Classifier: Topic :: System :: Networking :: Monitoring
Requires-Python: >=3.11
License-File: LICENSE
Requires-Dist: grpcio>=1.59.0
Requires-Dist: grpcio-tools>=1.59.0
Requires-Dist: protobuf>=4.25.1
Requires-Dist: psutil>=5.9.0
Requires-Dist: Flask>=2.3.0
Requires-Dist: Werkzeug>=2.3.0
Provides-Extra: dev
Requires-Dist: pytest>=7.0; extra == "dev"
Requires-Dist: black>=23.0; extra == "dev"
Requires-Dist: flake8>=5.0; extra == "dev"
Dynamic: home-page
Dynamic: license-file
Dynamic: requires-python
